AUTHORS
LICENSE
MANIFEST.in
README.rst
setup.py
tests.py
straight/__init__.py
straight.plugin.egg-info/PKG-INFO
straight.plugin.egg-info/SOURCES.txt
straight.plugin.egg-info/dependency_links.txt
straight.plugin.egg-info/namespace_packages.txt
straight.plugin.egg-info/top_level.txt
straight/plugin/__init__.py
straight/plugin/loaders.py
straight/plugin/manager.py
test-packages/class-test-plugins/testplugin/__init__.py
test-packages/class-test-plugins/testplugin/__init__.pyc
test-packages/class-test-plugins/testplugin/testclasses.py
test-packages/class-test-plugins/testplugin/testclasses.pyc
test-packages/class-test-plugins/testplugin/__pycache__/__init__.cpython-33.pyc
test-packages/class-test-plugins/testplugin/__pycache__/__init__.cpython-34.pyc
test-packages/class-test-plugins/testplugin/__pycache__/__init__.cpython-35.pyc
test-packages/class-test-plugins/testplugin/__pycache__/__init__.cpython-36.pyc
test-packages/class-test-plugins/testplugin/__pycache__/testclasses.cpython-33.pyc
test-packages/class-test-plugins/testplugin/__pycache__/testclasses.cpython-34.pyc
test-packages/class-test-plugins/testplugin/__pycache__/testclasses.cpython-35.pyc
test-packages/class-test-plugins/testplugin/__pycache__/testclasses.cpython-36.pyc
test-packages/imply-plugins/testplugin/__init__.py
test-packages/imply-plugins/testplugin/__init__.pyc
test-packages/imply-plugins/testplugin/foo.py
test-packages/imply-plugins/testplugin/foo.pyc
test-packages/imply-plugins/testplugin/__pycache__/__init__.cpython-33.pyc
test-packages/imply-plugins/testplugin/__pycache__/__init__.cpython-34.pyc
test-packages/imply-plugins/testplugin/__pycache__/__init__.cpython-35.pyc
test-packages/imply-plugins/testplugin/__pycache__/__init__.cpython-36.pyc
test-packages/imply-plugins/testplugin/__pycache__/foo.cpython-33.pyc
test-packages/imply-plugins/testplugin/__pycache__/foo.cpython-34.pyc
test-packages/imply-plugins/testplugin/__pycache__/foo.cpython-35.pyc
test-packages/imply-plugins/testplugin/__pycache__/foo.cpython-36.pyc
test-packages/imply-plugins/testplugin_2/__init__.py
test-packages/imply-plugins/testplugin_2/__init__.pyc
test-packages/imply-plugins/testplugin_2/bar.py
