Metadata-Version: 1.1
Name: straight.plugin
Version: 1.5.0
Summary: A simple namespaced plugin facility
Home-page: https://github.com/ironfroggy/straight.plugin
Author: Calvin Spealman
Author-email: ironfroggy@gmail.com
License: UNKNOWN
Platform: UNKNOWN
Classifier: Programming Language :: Python :: 2
Classifier: Programming Language :: Python :: 3
Classifier: Environment :: Plugins
